{
  "dangCauHoi": "P0_2",
  "elementType": "PRONUNCIATION",
  "danhSachCauHoi": [
    {
      "_id": {
        "$oid": "51a82e01-27b2-40cf-8254-e0007630cf93"
      },
      "cauHoiNho": [],
      "amThanh": "4SKILLS_MTC_L18/sounds/normal/MTC_18_PRONUNCIATION_1175.reporter.mp3",
      "amThanhCham": "4SKILLS_MTC_L18/sounds/slow/MTC_18_PRONUNCIATION_1175.reporter.mp3",
      "cauHoi": "Reporter /rɪˈpɔːtər/ (n): Phóng viên",
      "yNghia": "Phóng viên",
      "hinhAnh": "4SKILLS_MTC_L18/MTC_18_PRONUNCIATION_1175.reporter.png",
      "phienAm": "/rɪˈpɔːtər/",
      "loaiTu": "n",
      "tuKemTheo": "Reporter",
      "loaiBaiHoc": "IPA",
      "dangCauHoi": "IPA_1"
    },
    {
      "_id": {
        "$oid": "3c67d14b-d10d-41cf-bb62-98c3f578113c"
      },
      "cauHoiNho": [],
      "amThanh": "4SKILLS_MTC_L18/sounds/normal/MTC_18_PRONUNCIATION_1176.translator.mp3",
      "amThanhCham": "4SKILLS_MTC_L18/sounds/slow/MTC_18_PRONUNCIATION_1176.translator.mp3",
      "cauHoi": "Translator /trænsˈleɪtər/ (n): Phiên dịch viên, biên dịch viên",
      "yNghia": "Phiên dịch viên, biên dịch viên",
      "hinhAnh": "4SKILLS_MTC_L18/MTC_18_PRONUNCIATION_1176.translator.png",
      "phienAm": "/trænsˈleɪtər/",
      "loaiTu": "n",
      "tuKemTheo": "Translator",
      "loaiBaiHoc": "IPA",
      "dangCauHoi": "IPA_1"
    },
    {
      "_id": {
        "$oid": "b06ab26c-b1a5-40e9-a4f9-7131060b5139"
      },
      "cauHoiNho": [],
      "amThanh": "4SKILLS_MTC_L18/sounds/normal/MTC_18_PRONUNCIATION_1177.potential.mp3",
      "amThanhCham": "4SKILLS_MTC_L18/sounds/slow/MTC_18_PRONUNCIATION_1177.potential.mp3",
      "cauHoi": "Potential /pəˈtenʃəl/ (n): Tiềm năng",
      "yNghia": "Tiềm năng",
      "hinhAnh": "4SKILLS_MTC_L18/MTC_18_PRONUNCIATION_1177.potential.png",
      "phienAm": "/pəˈtenʃəl/",
      "loaiTu": "n",
      "tuKemTheo": "Potential",
      "loaiBaiHoc": "IPA",
      "dangCauHoi": "IPA_1"
    },
    {
      "_id": {
        "$oid": "96e1c9af-e09b-47d1-a8d1-a5611eb4c34d"
      },
      "cauHoiNho": [],
      "amThanh": "4SKILLS_MTC_L18/sounds/normal/MTC_18_PRONUNCIATION_1178.expert.mp3",
      "amThanhCham": "4SKILLS_MTC_L18/sounds/slow/MTC_18_PRONUNCIATION_1178.expert.mp3",
      "cauHoi": "Expert /ˈekspɜːt/ (n): Chuyên gia",
      "yNghia": "Chuyên gia",
      "hinhAnh": "4SKILLS_MTC_L18/MTC_18_PRONUNCIATION_1178.expert.png",
      "phienAm": "/ˈekspɜːt/",
      "loaiTu": "n",
      "tuKemTheo": "Expert",
      "loaiBaiHoc": "IPA",
      "dangCauHoi": "IPA_1"
    },
    {
      "_id": {
        "$oid": "e8c6ccc0-654e-40eb-b1c0-ef63cbe93c97"
      },
      "cauHoiNho": [],
      "amThanh": "4SKILLS_MTC_L18/sounds/normal/MTC_18_PRONUNCIATION_1179.media.mp3",
      "amThanhCham": "4SKILLS_MTC_L18/sounds/slow/MTC_18_PRONUNCIATION_1179.media.mp3",
      "cauHoi": "Media /ˈmiːdiə/ (n): Truyền thông",
      "yNghia": "Truyền thông",
      "hinhAnh": "4SKILLS_MTC_L18/MTC_18_PRONUNCIATION_1179.media.png",
      "phienAm": "/ˈmiːdiə/",
      "loaiTu": "n",
      "tuKemTheo": "Media",
      "loaiBaiHoc": "IPA",
      "dangCauHoi": "IPA_1"
    },
    {
      "_id": {
        "$oid": "ca8c4174-44b6-4d03-a369-bd236f56969a"
      },
      "cauHoiNho": [],
      "amThanh": "4SKILLS_MTC_L18/sounds/normal/MTC_18_PRONUNCIATION_1180.freelance.mp3",
      "amThanhCham": "4SKILLS_MTC_L18/sounds/slow/MTC_18_PRONUNCIATION_1180.freelance.mp3",
      "cauHoi": "Freelance /ˈfriːlɑːns/ (adj): Làm nghề tự do",
      "yNghia": "Làm nghề tự do",
      "hinhAnh": "4SKILLS_MTC_L18/MTC_18_PRONUNCIATION_1180.freelance.png",
      "phienAm": "/ˈfriːlɑːns/",
      "loaiTu": "adj",
      "tuKemTheo": "Freelance",
      "loaiBaiHoc": "IPA",
      "dangCauHoi": "IPA_1"
    },
    {
      "_id": {
        "$oid": "bad3ebb9-204c-44ba-8d02-94589fdc8cc7"
      },
      "cauHoiNho": [],
      "amThanh": "4SKILLS_MTC_L18/sounds/normal/MTC_18_PRONUNCIATION_1181.provide.mp3",
      "amThanhCham": "4SKILLS_MTC_L18/sounds/slow/MTC_18_PRONUNCIATION_1181.provide.mp3",
      "cauHoi": "Provide /prəˈvaɪd/ (v): Cung cấp",
      "yNghia": "Cung cấp",
      "hinhAnh": "4SKILLS_MTC_L18/MTC_18_PRONUNCIATION_1181.provide.png",
      "phienAm": "/prəˈvaɪd/",
      "loaiTu": "v",
      "tuKemTheo": "Provide",
      "loaiBaiHoc": "IPA",
      "dangCauHoi": "IPA_1"
    },
    {
      "_id": {
        "$oid": "c8ae69bd-3e1f-443b-b4ee-a4f5b85020ee"
      },
      "cauHoiNho": [],
      "amThanh": "4SKILLS_MTC_L18/sounds/normal/MTC_18_PRONUNCIATION_1182.foreign.correspondent.mp3",
      "amThanhCham": "4SKILLS_MTC_L18/sounds/slow/MTC_18_PRONUNCIATION_1182.foreign.correspondent.mp3",
      "cauHoi": "Foreign correspondent /ˈfɒrən ˌkɒrəˈspɒndənt/ (n.p): Phóng viên thường trực tại \n  nước ngoài",
      "yNghia": "Phóng viên thường trực tại \n  nước ngoài",
      "hinhAnh": "4SKILLS_MTC_L18/MTC_18_PRONUNCIATION_1182.foreign.correspondent.png",
      "phienAm": "/ˈfɒrən ˌkɒrəˈspɒndənt/",
      "loaiTu": "n.p",
      "tuKemTheo": "Foreign correspondent",
      "loaiBaiHoc": "IPA",
      "dangCauHoi": "IPA_1"
    },
    {
      "_id": {
        "$oid": "ab80e1b8-27d4-4c34-b42e-5c24f82c1e0d"
      },
      "cauHoiNho": [],
      "amThanh": "4SKILLS_MTC_L18/sounds/normal/MTC_18_PRONUNCIATION_1183.investigative.journalist.mp3",
      "amThanhCham": "4SKILLS_MTC_L18/sounds/slow/MTC_18_PRONUNCIATION_1183.investigative.journalist.mp3",
      "cauHoi": "Investigative journalist /ɪnˈvestɪɡətɪv ˈdʒɜːnəlɪst/ (n.p): Nhà báo điều tra",
      "yNghia": "Nhà báo điều tra",
      "hinhAnh": "4SKILLS_MTC_L18/MTC_18_PRONUNCIATION_1183.investigative.journalist.png",
      "phienAm": "/ɪnˈvestɪɡətɪv ˈdʒɜːnəlɪst/",
      "loaiTu": "n.p",
      "tuKemTheo": "Investigative journalist",
      "loaiBaiHoc": "IPA",
      "dangCauHoi": "IPA_1"
    },
    {
      "_id": {
        "$oid": "a18039b4-20d1-48d4-bade-38d2931ecee1"
      },
      "cauHoiNho": [],
      "amThanh": "4SKILLS_MTC_L18/sounds/normal/MTC_18_PRONUNCIATION_1184.photojournalist.mp3",
      "amThanhCham": "4SKILLS_MTC_L18/sounds/slow/MTC_18_PRONUNCIATION_1184.photojournalist.mp3",
      "cauHoi": "Photojournalist /ˌfəʊtəʊˈdʒɜːnəlɪst/ (n.p): Phóng viên ảnh",
      "yNghia": "Phóng viên ảnh",
      "hinhAnh": "4SKILLS_MTC_L18/MTC_18_PRONUNCIATION_1184.photojournalist.png",
      "phienAm": "/ˌfəʊtəʊˈdʒɜːnəlɪst/",
      "loaiTu": "n.p",
      "tuKemTheo": "Photojournalist",
      "loaiBaiHoc": "IPA",
      "dangCauHoi": "IPA_1"
    },
    {
      "_id": {
        "$oid": "6afb1ccf-d6f6-4af5-8924-ec486aa63b7a"
      },
      "cauHoiNho": [],
      "amThanh": "4SKILLS_MTC_L18/sounds/normal/MTC_18_PRONUNCIATION_1185.sports.journalist.mp3",
      "amThanhCham": "4SKILLS_MTC_L18/sounds/slow/MTC_18_PRONUNCIATION_1185.sports.journalist.mp3",
      "cauHoi": "Sports journalist /spɔːts ˈdʒɜːnəlɪst/ (n.p): Phóng viên thể thao",
      "yNghia": "Phóng viên thể thao",
      "hinhAnh": "4SKILLS_MTC_L18/MTC_18_PRONUNCIATION_1185.sports.journalist.png",
      "phienAm": "/spɔːts ˈdʒɜːnəlɪst/",
      "loaiTu": "n.p",
      "tuKemTheo": "Sports journalist",
      "loaiBaiHoc": "IPA",
      "dangCauHoi": "IPA_1"
    },
    {
      "_id": {
        "$oid": "94a90a3b-7571-4e28-9f04-4057c0caaa64"
      },
      "cauHoiNho": [],
      "amThanh": "4SKILLS_MTC_L18/sounds/normal/MTC_18_PRONUNCIATION_1186.news.anchor.mp3",
      "amThanhCham": "4SKILLS_MTC_L18/sounds/slow/MTC_18_PRONUNCIATION_1186.news.anchor.mp3",
      "cauHoi": "News anchor /njuːz ˈæŋkər/ (n.p): Người dẫn chương trình thời sự",
      "yNghia": "Người dẫn chương trình thời sự",
      "hinhAnh": "4SKILLS_MTC_L18/MTC_18_PRONUNCIATION_1186.news.anchor.png",
      "phienAm": "/njuːz ˈæŋkər/",
      "loaiTu": "n.p",
      "tuKemTheo": "News anchor",
      "loaiBaiHoc": "IPA",
      "dangCauHoi": "IPA_1"
    },
    {
      "_id": {
        "$oid": "0162d3c4-0882-45db-bf74-ac9fe253c836"
      },
      "cauHoiNho": [],
      "amThanh": "4SKILLS_MTC_L18/sounds/normal/MTC_18_PRONUNCIATION_1187.newspaper.editor.mp3",
      "amThanhCham": "4SKILLS_MTC_L18/sounds/slow/MTC_18_PRONUNCIATION_1187.newspaper.editor.mp3",
      "cauHoi": "Newspaper editor /ˈnjuːzˌpeɪpər ˈedɪtər/ (n.p): Biên tập viên báo chí",
      "yNghia": "Biên tập viên báo chí",
      "hinhAnh": "4SKILLS_MTC_L18/MTC_18_PRONUNCIATION_1187.newspaper.editor.png",
      "phienAm": "/ˈnjuːzˌpeɪpər ˈedɪtər/",
      "loaiTu": "n.p",
      "tuKemTheo": "Newspaper editor",
      "loaiBaiHoc": "IPA",
      "dangCauHoi": "IPA_1"
    },
    {
      "_id": {
        "$oid": "4d4ac21c-f5e2-4300-bff0-75094dab27e5"
      },
      "cauHoiNho": [],
      "amThanh": "4SKILLS_MTC_L18/sounds/normal/MTC_18_PRONUNCIATION_1188.a.degree.of.truth.mp3",
      "amThanhCham": "4SKILLS_MTC_L18/sounds/slow/MTC_18_PRONUNCIATION_1188.a.degree.of.truth.mp3",
      "cauHoi": "A degree of truth /eɪ dɪˈɡriː ɒv truːθ/ (n.p): Một phần nào đó của sự thật, \n  có phần đúng",
      "yNghia": "Một phần nào đó của sự thật, \n  có phần đúng",
      "hinhAnh": "4SKILLS_MTC_L18/MTC_18_PRONUNCIATION_1188.a.degree.of.truth.png",
      "phienAm": "/eɪ dɪˈɡriː ɒv truːθ/",
      "loaiTu": "n.p",
      "tuKemTheo": "A degree of truth",
      "loaiBaiHoc": "IPA",
      "dangCauHoi": "IPA_1"
    },
    {
      "_id": {
        "$oid": "fe709f48-d811-4649-9d1c-b0154ab02352"
      },
      "cauHoiNho": [],
      "amThanh": "4SKILLS_MTC_L18/sounds/normal/MTC_18_PRONUNCIATION_1189.international.relations.mp3",
      "amThanhCham": "4SKILLS_MTC_L18/sounds/slow/MTC_18_PRONUNCIATION_1189.international.relations.mp3",
      "cauHoi": "International relations /ˌɪntəˈnæʃənəl rɪˈleɪʃənz/ (n.p): Quan hệ quốc tế",
      "yNghia": "Quan hệ quốc tế",
      "hinhAnh": "4SKILLS_MTC_L18/MTC_18_PRONUNCIATION_1189.international.relations.png",
      "phienAm": "/ˌɪntəˈnæʃənəl rɪˈleɪʃənz/",
      "loaiTu": "n.p",
      "tuKemTheo": "International relations",
      "loaiBaiHoc": "IPA",
      "dangCauHoi": "IPA_1"
    },
    {
      "_id": {
        "$oid": "42ea1441-0217-46d2-a4eb-a2d161ea997f"
      },
      "cauHoiNho": [],
      "amThanh": "4SKILLS_MTC_L18/sounds/normal/MTC_18_PRONUNCIATION_1190.gather.information.mp3",
      "amThanhCham": "4SKILLS_MTC_L18/sounds/slow/MTC_18_PRONUNCIATION_1190.gather.information.mp3",
      "cauHoi": "Gather information /ˈɡæðər ˌɪnfəˈmeɪʃn/ (v.p): Thu thập thông tin",
      "yNghia": "Thu thập thông tin",
      "hinhAnh": "4SKILLS_MTC_L18/MTC_18_PRONUNCIATION_1190.gather.information.png",
      "phienAm": "/ˈɡæðər ˌɪnfəˈmeɪʃn/",
      "loaiTu": "v.p",
      "tuKemTheo": "Gather information",
      "loaiBaiHoc": "IPA",
      "dangCauHoi": "IPA_1"
    },
    {
      "_id": {
        "$oid": "d8f9e2c7-0610-4d01-a117-63eb5cc60413"
      },
      "cauHoiNho": [],
      "amThanh": "4SKILLS_MTC_L18/sounds/normal/MTC_18_PRONUNCIATION_17.Tournament.mp3",
      "amThanhCham": "4SKILLS_MTC_L18/sounds/slow/MTC_18_PRONUNCIATION_17.Tournament.mp3",
      "cauHoi": "Tournament /ˈtʊənəmənt/ (n): Giải đấu, giải đua",
      "yNghia": "Giải đấu, giải đua",
      "hinhAnh": "4SKILLS_MTC_L18/MTC_18_PRONUNCIATION_17.tournament.png",
      "phienAm": "/ˈtʊənəmənt/",
      "loaiTu": "n",
      "tuKemTheo": "Tournament",
      "loaiBaiHoc": "IPA",
      "dangCauHoi": "IPA_1"
    },
    {
      "_id": {
        "$oid": "c6fe4231-534a-4875-89df-d2d6e44041a4"
      },
      "cauHoiNho": [],
      "amThanh": "4SKILLS_MTC_L18/sounds/normal/MTC_18_PRONUNCIATION_18.Possibility.mp3",
      "amThanhCham": "4SKILLS_MTC_L18/sounds/slow/MTC_18_PRONUNCIATION_18.Possibility.mp3",
      "cauHoi": "Possibility /ˌpɒsəˈbɪləti/ (n): Khả năng",
      "yNghia": "Khả năng",
      "hinhAnh": "4SKILLS_MTC_L18/MTC_18_PRONUNCIATION_18.possibility.png",
      "phienAm": "/ˌpɒsəˈbɪləti/",
      "loaiTu": "n",
      "tuKemTheo": "Possibility",
      "loaiBaiHoc": "IPA",
      "dangCauHoi": "IPA_1"
    },
    {
      "_id": {
        "$oid": "e6920f11-0f7a-4051-a1ce-5bf602a15005"
      },
      "cauHoiNho": [],
      "amThanh": "4SKILLS_MTC_L18/sounds/normal/MTC_18_PRONUNCIATION_19.Suspected.mp3",
      "amThanhCham": "4SKILLS_MTC_L18/sounds/slow/MTC_18_PRONUNCIATION_19.Suspected.mp3",
      "cauHoi": "Suspected /səˈspektɪd/ (adj): Nghi ngờ, đáng ngờ",
      "yNghia": "Nghi ngờ, đáng ngờ",
      "hinhAnh": "4SKILLS_MTC_L18/MTC_18_PRONUNCIATION_19.suspected.png",
      "phienAm": "/səˈspektɪd/",
      "loaiTu": "adj",
      "tuKemTheo": "Suspected",
      "loaiBaiHoc": "IPA",
      "dangCauHoi": "IPA_1"
    },
    {
      "_id": {
        "$oid": "66a37da6-8c38-4c71-96d2-5d58aca4dc4e"
      },
      "cauHoiNho": [],
      "amThanh": "4SKILLS_MTC_L18/sounds/normal/MTC_18_PRONUNCIATION_20.Allergy.mp3",
      "amThanhCham": "4SKILLS_MTC_L18/sounds/slow/MTC_18_PRONUNCIATION_20.Allergy.mp3",
      "cauHoi": "Allergy /ˈælədʒi/ (n): Dị ứng",
      "yNghia": "Dị ứng",
      "hinhAnh": "4SKILLS_MTC_L18/MTC_18_PRONUNCIATION_20.allergy.png",
      "phienAm": "/ˈælədʒi/",
      "loaiTu": "n",
      "tuKemTheo": "Allergy",
      "loaiBaiHoc": "IPA",
      "dangCauHoi": "IPA_1"
    }
  ]
}