{
  "dangCauHoi": "P6",
  "elementType": "WRITING",
  "danhSachCauHoi": [
    {
      "_id": {
        "$oid": "88f4aaba-b824-400b-9a8a-cb72daf78e44"
      },
      "cauHoiNho": [],
      "yNghia": "Để mời ai đó tham gia một cách lịch sự, ta dùng cấu trúc: <b>Would you like to + participate in + danh từ</b>.<br />\r\nTa có: <b>our survey </b><i>(cuộc khảo sát của chúng tôi) </i>là danh từ, đứng sau cụm <b>participate in </b><i>(tham gia)</i>.<br />\r\nCâu hoàn chỉnh là <b><span style=\"color:red\">Would you like to participate in our survey? </span></b><i>(Bạn có muốn tham gia vào cuộc khảo sát của chúng tôi không?).</i>",
      "danhSachDapAn": [
        {
          "_id": {
            "$oid": "7a1f7734-edff-4f55-a410-4006261c1654"
          },
          "dapAn": "Would",
          "isCorrect": true
        },
        {
          "_id": {
            "$oid": "04ac3196-a14c-4c2e-8d8d-0d87e48384bb"
          },
          "dapAn": "you",
          "isCorrect": true
        },
        {
          "_id": {
            "$oid": "3b9047d1-5589-4557-bcf1-f0a14c172881"
          },
          "dapAn": "like to",
          "isCorrect": true
        },
        {
          "_id": {
            "$oid": "f3cb66bc-94ed-4d64-ab8f-cfade171408e"
          },
          "dapAn": "participate",
          "isCorrect": true
        },
        {
          "_id": {
            "$oid": "1e5b28bc-84d0-48e2-877a-7876e9d2ae76"
          },
          "dapAn": "in our",
          "isCorrect": true
        },
        {
          "_id": {
            "$oid": "7f56f261-f74e-44c6-b132-3b4483eb2b7a"
          },
          "dapAn": "survey?",
          "isCorrect": true
        }
      ]
    },
    {
      "_id": {
        "$oid": "8c070376-d007-4fcf-8e26-96ae01e11bcd"
      },
      "cauHoiNho": [],
      "yNghia": "Để hỏi ý kiến ai về thứ gì đó, ta dùng cấu trúc: <b>What's your opinion of + danh từ</b>.<br />\r\nTa có: <b>TV talent shows </b><i>(các chương trình tìm kiếm tài năng trên TV) </i>là danh từ đứng sau cụm <b>What's your opinion of </b><i>(Ý kiến ​​của bạn về ... là gì)</i>.<br />\r\nCâu hoàn chỉnh là <b><span style=\"color:red\">What's your opinion of TV talent shows? </span></b><i>(Ý kiến ​​của bạn về các chương trình tìm kiếm tài năng trên TV là gì?).</i>",
      "danhSachDapAn": [
        {
          "_id": {
            "$oid": "ddae9737-f17d-407b-b0ea-cf6f31634c31"
          },
          "dapAn": "What's",
          "isCorrect": true
        },
        {
          "_id": {
            "$oid": "13006fc9-dfac-4e57-b185-70634c803084"
          },
          "dapAn": "your",
          "isCorrect": true
        },
        {
          "_id": {
            "$oid": "d567fe03-9e02-4f6d-b020-8305d6015e36"
          },
          "dapAn": "opinion",
          "isCorrect": true
        },
        {
          "_id": {
            "$oid": "a7721c68-9e44-4037-97e7-91093178050f"
          },
          "dapAn": "of",
          "isCorrect": true
        },
        {
          "_id": {
            "$oid": "a228fb46-cea9-44ba-8882-d43cef0db59d"
          },
          "dapAn": "TV talent",
          "isCorrect": true
        },
        {
          "_id": {
            "$oid": "e9db832d-c9af-4e19-8b49-aae88176ff1c"
          },
          "dapAn": "shows?",
          "isCorrect": true
        }
      ]
    },
    {
      "_id": {
        "$oid": "095d03c8-eb15-4d0f-9d20-bf10a2c3dee4"
      },
      "cauHoiNho": [],
      "yNghia": "Để nói rằng về đặc điểm hoặc nội dung của một thứ gì đó, ta dùng cấu trúc: <b>It's + (very) + tính từ + (and) + (just) about + danh từ</b>.<br />\r\nTa có: <b>straightforward </b><i>(đơn giản) </i>là tính từ, <b>TV talent shows </b><i>(các chương trình tìm kiếm tài năng trên truyền) </i>là danh từ chỉ nội dung đứng sau cụm <b>just about </b><i>(chỉ nói về)</i>.<br />\r\nCâu hoàn chỉnh là <b><span style=\"color:red\">It's very straightforward and just about TV talent shows. </span></b><i>(Nó rất đơn giản và chỉ nói về các chương trình tìm kiếm tài năng trên truyền hình thôi.).</i>",
      "danhSachDapAn": [
        {
          "_id": {
            "$oid": "11f4a5f2-8b17-4775-aa12-3c406e95ef06"
          },
          "dapAn": "It's very",
          "isCorrect": true
        },
        {
          "_id": {
            "$oid": "4395c96d-ed62-4e1e-8d81-9bd70617d272"
          },
          "dapAn": "straightforward",
          "isCorrect": true
        },
        {
          "_id": {
            "$oid": "a041de42-1337-486e-8a22-7de88fe478b9"
          },
          "dapAn": "and just",
          "isCorrect": true
        },
        {
          "_id": {
            "$oid": "e43c16a3-2913-4384-a7d2-66b4ac8cc34a"
          },
          "dapAn": "about TV",
          "isCorrect": true
        },
        {
          "_id": {
            "$oid": "cbde8b1c-0a1e-4bd1-ab94-31cd7a47662f"
          },
          "dapAn": "talent",
          "isCorrect": true
        },
        {
          "_id": {
            "$oid": "d486d4d4-c2e7-4a02-a965-21693b5fb535"
          },
          "dapAn": "shows.",
          "isCorrect": true
        }
      ]
    },
    {
      "_id": {
        "$oid": "dd82caab-28e2-4097-83b6-3cbe738b450d"
      },
      "cauHoiNho": [],
      "yNghia": "Để đặt câu với trạng ngữ chỉ mức độ <b>quite a lot</b>, ta dùng cấu trúc: <b>Chủ ngữ + động từ + quite a lot + about + danh từ</b>.<br />\r\nTa có: <b>I </b><i>(Tôi) </i>là chủ ngữ, <b>know </b><i>(biết) </i>là động từ,<b> this kind of TV show </b><i>(loại chương trình truyền hình này) </i>là danh từ.<br />\r\nCâu hoàn chỉnh là <b><span style=\"color:red\">I know quite a lot about this kind of TV show. </span></b><i>(Tôi biết khá nhiều về loại chương trình truyền hình này.).</i>",
      "danhSachDapAn": [
        {
          "_id": {
            "$oid": "7bd5d338-57d4-4a97-9f50-a864a96b52fb"
          },
          "dapAn": "I know",
          "isCorrect": true
        },
        {
          "_id": {
            "$oid": "efe7ee22-70c7-4b7d-8391-60e8fa6f104c"
          },
          "dapAn": "quite a",
          "isCorrect": true
        },
        {
          "_id": {
            "$oid": "66bc2e64-4288-42ac-b6d8-15e4e048acb7"
          },
          "dapAn": "lot about",
          "isCorrect": true
        },
        {
          "_id": {
            "$oid": "33537b6f-2d1d-4bc5-8e72-a2bc40c594c3"
          },
          "dapAn": "this",
          "isCorrect": true
        },
        {
          "_id": {
            "$oid": "1afa8334-0108-4907-bd0a-65b996543656"
          },
          "dapAn": "kind of",
          "isCorrect": true
        },
        {
          "_id": {
            "$oid": "afa06058-4b0a-4cb4-a8fd-3759369270f4"
          },
          "dapAn": "TV show.",
          "isCorrect": true
        }
      ]
    },
    {
      "_id": {
        "$oid": "57ee6b70-f7fc-4dee-9286-c9110a5d2700"
      },
      "cauHoiNho": [],
      "yNghia": "Để đặt câu hỏi về tần suất của một hoạt động, ta dùng cấu trúc: <b>How often do you + động từ (nguyên thể) + bổ ngữ</b>.<br />\r\nTa có: <b>watch </b><i>(xem) </i>là động từ (nguyên thể), <b>TV talent shows </b><i>(các chương trình tìm kiếm tài năng trên TV) </i>là bổ ngữ.<br />\r\nCâu hoàn chỉnh là <b><span style=\"color:red\">How often do you watch TV talent shows? </span></b><i>(Bạn có thường xuyên xem các chương trình tìm kiếm tài năng trên TV không?).</i>",
      "danhSachDapAn": [
        {
          "_id": {
            "$oid": "fadea320-3141-416f-a53b-acc434405600"
          },
          "dapAn": "How",
          "isCorrect": true
        },
        {
          "_id": {
            "$oid": "b4015482-4a01-496a-9d59-5751ada621c0"
          },
          "dapAn": "often do",
          "isCorrect": true
        },
        {
          "_id": {
            "$oid": "b3587a5f-185a-4325-9ed3-efd5cd23f6e3"
          },
          "dapAn": "you",
          "isCorrect": true
        },
        {
          "_id": {
            "$oid": "02442b6e-0f36-4e99-af24-58aa57347fd8"
          },
          "dapAn": "watch",
          "isCorrect": true
        },
        {
          "_id": {
            "$oid": "b96bf647-5290-47c7-8115-7926408e047f"
          },
          "dapAn": "TV talent",
          "isCorrect": true
        },
        {
          "_id": {
            "$oid": "50d410b6-6cd3-417d-b9b7-5b1d9dd1c320"
          },
          "dapAn": "shows?",
          "isCorrect": true
        }
      ]
    },
    {
      "_id": {
        "$oid": "de7f4e1c-77d6-43d7-bae3-74cdbba9fcf7"
      },
      "cauHoiNho": [],
      "yNghia": "Để đặt câu với cụm <b>I think</b>, ta dùng cấu trúc: <b>I think + mệnh đề</b>.<br />\r\nTa có: <b>there are many great talent shows out there with lots of talented people </b><i>(có rất nhiều chương trình tìm kiếm tài năng tuyệt vời với rất nhiều người tài năng) </i>là mệnh đề đứng sau cụm <b>I think </b><i>(Tôi nghĩ rằng)</i>.<br />\r\nCâu hoàn chỉnh là <b><span style=\"color:red\">I think there are many great talent shows out there with lots of talented people. </span></b><i>(Tôi nghĩ rằng có rất nhiều chương trình tìm kiếm tài năng tuyệt vời với rất nhiều người tài năng.).</i>",
      "danhSachDapAn": [
        {
          "_id": {
            "$oid": "8847cfac-feb7-4d78-a005-2ec27e5ea66e"
          },
          "dapAn": "I think there",
          "isCorrect": true
        },
        {
          "_id": {
            "$oid": "b7ac8204-927e-4da3-88bc-40eed2a44110"
          },
          "dapAn": "are many",
          "isCorrect": true
        },
        {
          "_id": {
            "$oid": "9c2cf216-f44e-467e-a289-c95d30e97a76"
          },
          "dapAn": "great talent shows",
          "isCorrect": true
        },
        {
          "_id": {
            "$oid": "75ff79fe-66e6-41d4-a5a9-dcd52897b96b"
          },
          "dapAn": "out there",
          "isCorrect": true
        },
        {
          "_id": {
            "$oid": "756fd8e8-5e0f-4747-9828-2380ec609dd3"
          },
          "dapAn": "with lots of",
          "isCorrect": true
        },
        {
          "_id": {
            "$oid": "70bcf6c0-8da0-4d0c-92fe-9a1e532a725b"
          },
          "dapAn": "talented people.",
          "isCorrect": true
        }
      ]
    },
    {
      "_id": {
        "$oid": "a2f712b2-14d5-49c7-8fea-aee11fc68a51"
      },
      "cauHoiNho": [],
      "yNghia": "Để đặt câu với cụm <b>Is there</b>, ta dùng cấu trúc: <b>Is there + a + danh từ số it + mệnh đề quan hệ</b>.<br />\r\nTa có: <b>particular show </b><i>(chương trình cụ thể) </i>là danh từ số ít, <b>that is your favorite </b><i>(chương trình yêu thích của bạn) </i>là mệnh đề quan hệ bổ sung ý nghĩa cho danh từ <b>particular show</b>.<br />\r\nCâu hoàn chỉnh là <b><span style=\"color:red\">Is there a particular show that is your favorite? </span></b><i>(Có chương trình cụ thể nào là chương trình yêu thích của bạn không?).</i>",
      "danhSachDapAn": [
        {
          "_id": {
            "$oid": "9fece176-6092-4690-a8ff-3e941bd398b6"
          },
          "dapAn": "Is there a",
          "isCorrect": true
        },
        {
          "_id": {
            "$oid": "4d58ab0d-82ef-4e69-b75b-9bc246f6781c"
          },
          "dapAn": "particular",
          "isCorrect": true
        },
        {
          "_id": {
            "$oid": "83cfd8de-31fa-4fa3-b6da-bdb026ca6734"
          },
          "dapAn": "show",
          "isCorrect": true
        },
        {
          "_id": {
            "$oid": "61fb62e1-2efd-45b2-9640-ea4ef64ddee2"
          },
          "dapAn": "that is",
          "isCorrect": true
        },
        {
          "_id": {
            "$oid": "b18edd35-228b-4968-906f-cc801e54ff23"
          },
          "dapAn": "your",
          "isCorrect": true
        },
        {
          "_id": {
            "$oid": "7996345b-57d6-4f4a-b9a6-b2abe81313c8"
          },
          "dapAn": "favorite?",
          "isCorrect": true
        }
      ]
    },
    {
      "_id": {
        "$oid": "d0fd81a4-cc59-47a6-b7a5-732dd4c4c1aa"
      },
      "cauHoiNho": [],
      "yNghia": "Để nói rằng tôi thích cái gì nhất, ta dùng cấu trúc: <b>I like + tân ngữ + the best</b>.<br />\r\nTa có: <b>the show Dance Off </b><i>(chương trình Dance Off) </i>là tân ngữ đứng sau cụm <b>I like </b><i>(Tôi thích)</i>.<br />\r\nCâu hoàn chỉnh là <b><span style=\"color:red\">I like the show Dance Off the best. </span></b><i>(Tôi thích chương trình Dance Off nhất.).</i>",
      "danhSachDapAn": [
        {
          "_id": {
            "$oid": "c6c99a6a-9f15-4ef7-ab2f-dae5e020949f"
          },
          "dapAn": "I",
          "isCorrect": true
        },
        {
          "_id": {
            "$oid": "5a5c2f4f-38f7-4d87-9e60-2b5f7d9dcbac"
          },
          "dapAn": "like",
          "isCorrect": true
        },
        {
          "_id": {
            "$oid": "1b306495-ec45-414d-a621-24f10563681a"
          },
          "dapAn": "the",
          "isCorrect": true
        },
        {
          "_id": {
            "$oid": "a3f46482-2d9b-4d7b-9955-e134883e4091"
          },
          "dapAn": "show",
          "isCorrect": true
        },
        {
          "_id": {
            "$oid": "66d91cb7-2c25-48ae-abe9-48c4b69a4508"
          },
          "dapAn": "Dance Off",
          "isCorrect": true
        },
        {
          "_id": {
            "$oid": "f4dee9c7-3b84-4c17-a30c-00d79e407bda"
          },
          "dapAn": "the best.",
          "isCorrect": true
        }
      ]
    },
    {
      "_id": {
        "$oid": "f6a63885-1ca8-499b-bfb4-57831de25ca0"
      },
      "cauHoiNho": [],
      "yNghia": "Để hỏi thêm thông tin chi tiết về vấn đề nào đó, ta dùng cấu trúc: <b>Can you tell more about + tân ngữ</b>.<br />\r\nTa có: <b>your sister's journey in the show </b><i>(hành trình của em gái mình trong chương trình đó) </i>là tân ngữ, đứng sau cụm <b>Can you tell more about </b><i>(Bạn có thể kể thêm về)</i>.<br />\r\nCâu hoàn chỉnh là <b><span style=\"color:red\">Can you tell more about your sister's journey in the show? </span></b><i>(Bạn có thể kể thêm về hành trình của em gái mình trong chương trình đó không?).</i>",
      "danhSachDapAn": [
        {
          "_id": {
            "$oid": "531c7c59-58ab-441d-b885-d067e64550e8"
          },
          "dapAn": "Can",
          "isCorrect": true
        },
        {
          "_id": {
            "$oid": "40891d48-7211-4885-bc91-419b14f924e6"
          },
          "dapAn": "you tell",
          "isCorrect": true
        },
        {
          "_id": {
            "$oid": "f0dd44f9-84ba-42bb-bf6e-4c13806f37a4"
          },
          "dapAn": "more about",
          "isCorrect": true
        },
        {
          "_id": {
            "$oid": "43e7c846-6fd2-4cca-a1d7-4a9cc71ba0cb"
          },
          "dapAn": "your sister's",
          "isCorrect": true
        },
        {
          "_id": {
            "$oid": "d4033da1-8113-412b-9e2b-1c679cf6571c"
          },
          "dapAn": "journey in",
          "isCorrect": true
        },
        {
          "_id": {
            "$oid": "e14abdb9-13e5-44da-9b96-72e5215fc180"
          },
          "dapAn": "the show?",
          "isCorrect": true
        }
      ]
    },
    {
      "_id": {
        "$oid": "f8d9af9f-8339-4dd2-82b6-1cb345c66a95"
      },
      "cauHoiNho": [],
      "yNghia": "Để diễn tả 2 hành động liên tiếp xảy ra trong quá khứ, ta dùng cấu trúc: <b>Chủ ngữ + động từ (quá khứ đơn) 1 + trạng ngữ 1 + động từ (quá khứ đơn) 2 + trạng ngữ 2</b>.<br />\r\nTa có: <b>danced </b><i>(đã nhảy) </i>là động từ (quá khứ đơn) 1, <b>with a professional dancer </b><i>(với một vũ công chuyên nghiệp) </i>là trạng ngữ 1, <b>came in </b><i>(xếp hạng) </i>là động từ (quá khứ đơn) 2,<b> second place </b><i>(vị trí thứ hai) </i>là trạng ngữ 2.<br />\r\nCâu hoàn chỉnh là <b><span style=\"color:red\">She danced with a professional dancer and came in second place. </span></b><i>(Em ấy đã nhảy với một vũ công chuyên nghiệp và xếp hạng ở vị trí thứ hai.).</i>",
      "danhSachDapAn": [
        {
          "_id": {
            "$oid": "999e1e43-14ab-40d3-b8d9-6c030c93f1d2"
          },
          "dapAn": "She danced",
          "isCorrect": true
        },
        {
          "_id": {
            "$oid": "72896449-eb39-4c76-b032-6164b3814e7d"
          },
          "dapAn": "with a",
          "isCorrect": true
        },
        {
          "_id": {
            "$oid": "f302bca0-1688-4b68-a05c-f025335a0c51"
          },
          "dapAn": "professional",
          "isCorrect": true
        },
        {
          "_id": {
            "$oid": "03103709-ac4b-46b8-8884-3090afa4fca4"
          },
          "dapAn": "dancer and",
          "isCorrect": true
        },
        {
          "_id": {
            "$oid": "8df41356-8c88-4a0e-b70b-55b2ca4a1167"
          },
          "dapAn": "came in",
          "isCorrect": true
        },
        {
          "_id": {
            "$oid": "47b135e0-284f-4d88-9889-e9daf00811a5"
          },
          "dapAn": "second place.",
          "isCorrect": true
        }
      ]
    },
    {
      "_id": {
        "$oid": "15cdd8b8-6eda-43a0-87ce-d91e7291e48f"
      },
      "cauHoiNho": [],
      "yNghia": "Để hỏi ý kiến của ai đó về một vấn đề, ta dùng cấu trúc: <b>Do you think + chủ ngữ + động từ (hiện tại đơn) + danh từ + mệnh đề quan hệ</b>.<br />\r\nTa có: <b>some talent shows </b><i>(một số chương trình tìm kiếm tài năng) </i>là chủ ngữ, <b>feature </b><i>(có) </i>là động từ (hiện tại đơn), <b>people </b><i>(những người) </i>là danh từ đứng sau động từ <b>feature</b>, <b>who aren't very talented </b><i>(người không tài năng lắm) </i>là mệnh đề quan hệ bổ sung ý nghĩa cho tân ngữ.<br />\r\nCâu hoàn chỉnh là <b><span style=\"color:red\">Do you think some talent shows feature people who aren't very talented? </span></b><i>(Bạn có nghĩ rằng một số chương trình tìm kiếm tài năng có những người không tài năng lắm không?).</i>",
      "danhSachDapAn": [
        {
          "_id": {
            "$oid": "2ea24cbf-8bf5-4a5a-bec0-9a5243accc08"
          },
          "dapAn": "Do you",
          "isCorrect": true
        },
        {
          "_id": {
            "$oid": "7890e2c9-f9b1-4fc9-abf3-a48788ee2ea4"
          },
          "dapAn": "think some",
          "isCorrect": true
        },
        {
          "_id": {
            "$oid": "1a6d75c9-d998-425a-b96a-92d32ef43bd4"
          },
          "dapAn": "talent shows",
          "isCorrect": true
        },
        {
          "_id": {
            "$oid": "2aaddbf3-74a4-49a4-9755-de4faba775f8"
          },
          "dapAn": "feature people",
          "isCorrect": true
        },
        {
          "_id": {
            "$oid": "e8a3a8dd-096b-4487-9aa5-ea7f32c31a3e"
          },
          "dapAn": "who aren't",
          "isCorrect": true
        },
        {
          "_id": {
            "$oid": "2ede8f00-9788-410c-bb23-0d8fdecc5277"
          },
          "dapAn": "very talented?",
          "isCorrect": true
        }
      ]
    },
    {
      "_id": {
        "$oid": "653f43ee-1022-49c5-a1c6-bbeef0bef8e0"
      },
      "cauHoiNho": [],
      "yNghia": "Để đặt câu với cụm <b>I think</b>, ta dùng cấu trúc: <b>I think + mệnh đề</b>.<br />\r\nTa có: <b>it's interesting to hear what the judges say </b><i>(thật thú vị khi nghe những gì ban giám khảo nói) </i>là mệnh đề sau cụm <b>I think </b><i>(Tôi nghĩ)</i>.<br />\r\nCâu hoàn chỉnh là <b><span style=\"color:red\">I think it's interesting to hear what the judges say. </span></b><i>(Tôi nghĩ thật thú vị khi nghe những gì ban giám khảo nói.).</i>",
      "danhSachDapAn": [
        {
          "_id": {
            "$oid": "09af4c14-31a7-4223-bf5c-0b0864095527"
          },
          "dapAn": "I think",
          "isCorrect": true
        },
        {
          "_id": {
            "$oid": "cd031c01-a35a-41ab-bf9f-47bbc75244a1"
          },
          "dapAn": "it's",
          "isCorrect": true
        },
        {
          "_id": {
            "$oid": "7349c720-a8da-4c33-b7a6-298696541745"
          },
          "dapAn": "interesting",
          "isCorrect": true
        },
        {
          "_id": {
            "$oid": "af7011f7-1903-483d-9df7-590e0f06f63f"
          },
          "dapAn": "to hear",
          "isCorrect": true
        },
        {
          "_id": {
            "$oid": "92a42d71-3ba1-4a8a-8684-8ad3d472a7eb"
          },
          "dapAn": "what the",
          "isCorrect": true
        },
        {
          "_id": {
            "$oid": "179ada5e-6392-4c0a-88d3-88ccda210131"
          },
          "dapAn": "judges say.",
          "isCorrect": true
        }
      ]
    },
    {
      "_id": {
        "$oid": "5c17222a-266c-4556-b1ad-15f364fe117a"
      },
      "cauHoiNho": [],
      "yNghia": "Để nói rằng điều gì là rất khó, ta dùng cấu trúc: <b>It's very hard to + động từ (nguyên thể) + danh từ</b>.<br />\r\nTa có: <b>control </b><i>(kiểm soát) </i>là động từ (nguyên thể),<b> this problem </b><i>(vấn đề này) </i>là danh từ.<br />\r\nCâu hoàn chỉnh là <b><span style=\"color:red\">It's very hard to control this problem. </span></b><i>(Rất khó để kiểm soát vấn đề này.).</i>",
      "danhSachDapAn": [
        {
          "_id": {
            "$oid": "49b85345-ef1a-41a7-8e44-b9d866e781bb"
          },
          "dapAn": "It's",
          "isCorrect": true
        },
        {
          "_id": {
            "$oid": "39001686-4024-4299-bfb1-2cb3d99c7dd9"
          },
          "dapAn": "very",
          "isCorrect": true
        },
        {
          "_id": {
            "$oid": "e0621390-6ed1-41be-9cfa-b0cae18f178f"
          },
          "dapAn": "hard to",
          "isCorrect": true
        },
        {
          "_id": {
            "$oid": "67848ebf-f793-4a74-9577-0a3f64fd58f2"
          },
          "dapAn": "control",
          "isCorrect": true
        },
        {
          "_id": {
            "$oid": "135cb1ca-74c0-4469-994f-e0cf8663de3c"
          },
          "dapAn": "this",
          "isCorrect": true
        },
        {
          "_id": {
            "$oid": "d9f298db-46b4-4f41-b86f-233300001e4f"
          },
          "dapAn": "problem.",
          "isCorrect": true
        }
      ]
    },
    {
      "_id": {
        "$oid": "edfd8c86-18a7-4e80-8492-4780f4dbd475"
      },
      "cauHoiNho": [],
      "yNghia": "Để đặt câu với cụm <b>I think</b>, ta dùng cấu trúc: <b>I think + mệnh đề</b>.<br />\r\nTa có: <b>the level of talent in shows today is higher than it used to be </b><i>(mức độ tài năng trong các chương trình ngày nay cao hơn trước đây) </i>là mệnh đề đứng sau cụm <b>I think </b><i>(Tôi nghĩ)</i>.<br />\r\nCâu hoàn chỉnh là <b><span style=\"color:red\">I think the level of talent in shows today is higher than it used to be. </span></b><i>(Tôi nghĩ mức độ tài năng trong các chương trình ngày nay cao hơn trước đây.).</i>",
      "danhSachDapAn": [
        {
          "_id": {
            "$oid": "9d5af4f8-b20b-4e2e-9049-b7a685420477"
          },
          "dapAn": "I think the",
          "isCorrect": true
        },
        {
          "_id": {
            "$oid": "5dbe44bb-2a6f-4c26-b182-8542daac3bc1"
          },
          "dapAn": "level of talent",
          "isCorrect": true
        },
        {
          "_id": {
            "$oid": "81ba8d32-8e32-4c2f-8aa4-81e8f9a29ec2"
          },
          "dapAn": "in shows",
          "isCorrect": true
        },
        {
          "_id": {
            "$oid": "f3a62ad0-abc1-4d8f-a4fb-ea812b55fa2d"
          },
          "dapAn": "today is",
          "isCorrect": true
        },
        {
          "_id": {
            "$oid": "79841ccf-9dcc-43a9-afd0-1e8bf2c05bc7"
          },
          "dapAn": "higher than it",
          "isCorrect": true
        },
        {
          "_id": {
            "$oid": "63966b2c-e4cd-4e12-82a3-baf5c183383b"
          },
          "dapAn": "used to be.",
          "isCorrect": true
        }
      ]
    },
    {
      "_id": {
        "$oid": "e996e506-7ada-487a-b53a-d5d4f0d531e3"
      },
      "cauHoiNho": [],
      "yNghia": "Để diễn tả một phương pháp tốt, ta dùng cấu trúc: <b>Chủ ngữ + to be + a good method of + danh động từ + danh từ</b>.<br />\r\nTa có: <b>These shows </b><i>(Những chương trình này) </i>là chủ ngữ, sau danh động từ <b>finding </b><i>(tìm kiếm) </i>là danh từ <b>talented people </b><i>(những người tài năng)</i>.<br />\r\nCâu hoàn chỉnh là <b><span style=\"color:red\">These shows are a good method of finding talented people. </span></b><i>(Những chương trình này là một phương pháp tốt để tìm kiếm những người tài năng.).</i>",
      "danhSachDapAn": [
        {
          "_id": {
            "$oid": "b290a255-9bdc-457c-823b-537b5dd29a77"
          },
          "dapAn": "These",
          "isCorrect": true
        },
        {
          "_id": {
            "$oid": "a00ebfb1-17ce-4c72-8b3c-54aadcb0b48a"
          },
          "dapAn": "shows are",
          "isCorrect": true
        },
        {
          "_id": {
            "$oid": "9b56f87c-aea9-46bf-a0db-9e05ef7e3725"
          },
          "dapAn": "a good",
          "isCorrect": true
        },
        {
          "_id": {
            "$oid": "c16088fb-8869-44a5-9dbe-df6634420190"
          },
          "dapAn": "method",
          "isCorrect": true
        },
        {
          "_id": {
            "$oid": "8b42968c-6e28-4481-a328-5ff00e814231"
          },
          "dapAn": "of finding",
          "isCorrect": true
        },
        {
          "_id": {
            "$oid": "e7b47b1e-00be-4062-889a-d7c4b1b213f7"
          },
          "dapAn": "talented people.",
          "isCorrect": true
        }
      ]
    },
    {
      "_id": {
        "$oid": "c556fffa-b21a-431a-be7d-d59cf68aa77d"
      },
      "cauHoiNho": [],
      "yNghia": "Để đặt câu với cụm <b>I wanted to know how</b>, ta dùng cấu trúc: <b>I wanted to know how + mệnh đề</b>.<br />\r\nTa có: <b>I can start my own music company like you </b><i>(tôi có thể thành lập công ty âm nhạc của riêng mình giống như bạn) </i>là mệnh đề đứng sau cụm <b>I wanted to know how </b><i>(Tôi muốn biết làm thế nào)</i>. <br />\r\nCâu hoàn chỉnh là <b><span style=\"color:red\">I wanted to know how I can start my own music company like you. </span></b><i>(Tôi muốn biết làm thế nào tôi có thể thành lập công ty âm nhạc của riêng mình giống như bạn.).</i>",
      "danhSachDapAn": [
        {
          "_id": {
            "$oid": "efd55e4f-4aca-47f8-ae14-7ac14d507666"
          },
          "dapAn": "I wanted to",
          "isCorrect": true
        },
        {
          "_id": {
            "$oid": "9743025f-5ec9-4738-8394-b14551122f89"
          },
          "dapAn": "know how",
          "isCorrect": true
        },
        {
          "_id": {
            "$oid": "e6015e21-8d3c-497a-b07b-bc404213ddb8"
          },
          "dapAn": "I can start",
          "isCorrect": true
        },
        {
          "_id": {
            "$oid": "0c3f1f05-44e5-43e3-a625-ab926de813f2"
          },
          "dapAn": "my own music",
          "isCorrect": true
        },
        {
          "_id": {
            "$oid": "724b3779-d6a1-4c8d-9066-7b08be135ebd"
          },
          "dapAn": "company",
          "isCorrect": true
        },
        {
          "_id": {
            "$oid": "3f1d8555-748d-4ef7-81f2-8adcf3c02593"
          },
          "dapAn": "like you.",
          "isCorrect": true
        }
      ]
    },
    {
      "_id": {
        "$oid": "331b77ca-57bf-46c5-a389-3faa60c49275"
      },
      "cauHoiNho": [],
      "yNghia": "Để đặt câu mệnh lệnh với <b>Remember that</b>, ta dùng cấu trúc: <b>Remember that + mệnh đề</b>.<br />\r\nTa có: <b>music industry success is not about what you know, but who you know </b><i>(thành công trong ngành công nghiệp âm nhạc không phải là bạn biết được những gì mà là bạn biết được những ai) </i>là mệnh đề đứng sau cụm <b>Remember that </b><i>(Hãy nhớ rằng)</i>.<br />\r\nCâu hoàn chỉnh là <b><span style=\"color:red\">Remember that music industry success is not about what you know, but who you know. </span></b><i>(Hãy nhớ rằng thành công trong ngành công nghiệp âm nhạc không phải là bạn biết được những gì mà là bạn biết được những ai.).</i>",
      "danhSachDapAn": [
        {
          "_id": {
            "$oid": "dddc2359-8a7f-403b-8982-de7f99e8d94f"
          },
          "dapAn": "Remember that music",
          "isCorrect": true
        },
        {
          "_id": {
            "$oid": "321cac4e-9a03-45f4-8ed1-71e4e09a4d14"
          },
          "dapAn": "industry success",
          "isCorrect": true
        },
        {
          "_id": {
            "$oid": "b460e03f-de3a-444d-b3d4-92641839ff2f"
          },
          "dapAn": "is not about",
          "isCorrect": true
        },
        {
          "_id": {
            "$oid": "61adb2ea-14ba-4e02-84f7-df94f5f9fd81"
          },
          "dapAn": "what you know,",
          "isCorrect": true
        },
        {
          "_id": {
            "$oid": "d145c56a-0c96-445c-9708-d7b2bdabedf6"
          },
          "dapAn": "but who",
          "isCorrect": true
        },
        {
          "_id": {
            "$oid": "c0c45dee-8f3f-44da-bdf8-a88f2ff9177f"
          },
          "dapAn": "you know.",
          "isCorrect": true
        }
      ]
    },
    {
      "_id": {
        "$oid": "ef1a096b-2c72-4a13-b459-9b92f81e1ebe"
      },
      "cauHoiNho": [],
      "yNghia": "Để nói rằng tôi muốn làm gì, ta dùng cấu trúc: <b>I'd like to + động từ (nguyên thể) + tân ngữ gián tiếp + tân ngữ trực tiếp</b>.<br />\r\nTa có: <b>ask </b><i>(hỏi) </i>là động từ (nguyên thể), <b>Elsa </b>là tân ngữ gián tiếp và <b>how I can become a singer </b><i>(làm thế nào tôi có thể trở thành một ca sĩ) </i>là tân ngữ trực tiếp.<br />\r\nCâu hoàn chỉnh là <b><span style=\"color:red\">I'd like to ask Elsa how I can become a singer. </span></b><i>(Tôi muốn hỏi Elsa làm thế nào tôi có thể trở thành một ca sĩ.).</i>",
      "danhSachDapAn": [
        {
          "_id": {
            "$oid": "383368c9-b240-483d-a878-9222d8293b9c"
          },
          "dapAn": "I'd like",
          "isCorrect": true
        },
        {
          "_id": {
            "$oid": "b5672272-6373-4f4e-a12f-8ace988db4d3"
          },
          "dapAn": "to ask",
          "isCorrect": true
        },
        {
          "_id": {
            "$oid": "7d3f4200-c309-4641-909d-b3b6b704769a"
          },
          "dapAn": "Elsa how",
          "isCorrect": true
        },
        {
          "_id": {
            "$oid": "0a650fc0-33e8-4893-8037-c1dbc120d2d4"
          },
          "dapAn": "I can",
          "isCorrect": true
        },
        {
          "_id": {
            "$oid": "e741886e-61ff-4588-b382-89bca5b2e3b1"
          },
          "dapAn": "become",
          "isCorrect": true
        },
        {
          "_id": {
            "$oid": "ad1c77c5-b8e3-46ff-b281-cd6539ead6c4"
          },
          "dapAn": "a singer.",
          "isCorrect": true
        }
      ]
    },
    {
      "_id": {
        "$oid": "730d266a-f161-4074-9a22-73ab02f05aa8"
      },
      "cauHoiNho": [],
      "yNghia": "Để đặt câu với cụm <b>I think</b>, ta dùng cấu trúc: <b>I think + mệnh đề</b>.<br />\r\nTa có: <b>I have a good voice, but I don't know where to start </b><i>(tôi có một giọng hát tốt, nhưng tôi không biết bắt đầu từ đâu) </i>là mệnh đề đứng sau cụm <b>I think </b><i>(Tôi nghĩ rằng)</i>.<br />\r\nCâu hoàn chỉnh là <b><span style=\"color:red\">I think I have a good voice, but I don't know where to start. </span></b><i>(Tôi nghĩ rằng tôi có một giọng hát tốt, nhưng tôi không biết bắt đầu từ đâu.).</i>",
      "danhSachDapAn": [
        {
          "_id": {
            "$oid": "e6fc5de7-5a88-44fd-9609-749b1b41e408"
          },
          "dapAn": "I think I",
          "isCorrect": true
        },
        {
          "_id": {
            "$oid": "542d3ffa-c329-4ec6-840c-a8caf81411f9"
          },
          "dapAn": "have a",
          "isCorrect": true
        },
        {
          "_id": {
            "$oid": "e7614639-0f32-4f53-9c67-0c4a609d532d"
          },
          "dapAn": "good voice,",
          "isCorrect": true
        },
        {
          "_id": {
            "$oid": "e53f0cc7-20bd-488a-813c-c1c1262cd229"
          },
          "dapAn": "but I don't",
          "isCorrect": true
        },
        {
          "_id": {
            "$oid": "a8eaaa0e-5829-43cc-976e-7383b86cf342"
          },
          "dapAn": "know where",
          "isCorrect": true
        },
        {
          "_id": {
            "$oid": "26e3bb39-0043-424b-9832-5d3537b35601"
          },
          "dapAn": "to start.",
          "isCorrect": true
        }
      ]
    },
    {
      "_id": {
        "$oid": "2ef1a0d7-ba67-47c3-9082-3c3e383b0561"
      },
      "cauHoiNho": [],
      "yNghia": "Để khuyên ai đó cần phải làm những gì, ta dùng cấu trúc: <b>You need + to động từ (nguyên thể) 1 + bổ ngữ 1 + and + to động từ (nguyên thể) 2 + bổ ngữ 2. </b><br />\r\nTa có: <b>to think </b><i>(suy nghĩ) </i>là động từ (to + nguyên thể) 1, <b>about</b> <b>your goals </b><i>(về các mục tiêu của mình) </i>là bổ ngữ,<b> to remember </b><i>(nhớ giữ)</i><b> </b>là động từ (to + nguyên thể) 2,<b> to keep them small </b><i>(giữ chúng ở mức nhỏ) </i>là bổ ngữ 2.<br />\r\nCâu hoàn chỉnh là <b><span style=\"color:red\">You need to think about your goals and remember to keep them small.</span></b> <i>(Bạn cần suy nghĩ về các mục tiêu của mình và nhớ giữ chúng ở mức nhỏ.).</i>",
      "danhSachDapAn": [
        {
          "_id": {
            "$oid": "a0803694-6f60-4189-b5c5-7069583daf66"
          },
          "dapAn": "You need to",
          "isCorrect": true
        },
        {
          "_id": {
            "$oid": "b73197b7-d733-4148-8362-5a0d993fd9ab"
          },
          "dapAn": "think about",
          "isCorrect": true
        },
        {
          "_id": {
            "$oid": "3ad0d8ff-0f93-4582-867e-0ad65cd52de0"
          },
          "dapAn": "your goals",
          "isCorrect": true
        },
        {
          "_id": {
            "$oid": "db4caf80-83da-469d-ba42-ce062b838af7"
          },
          "dapAn": "and remember",
          "isCorrect": true
        },
        {
          "_id": {
            "$oid": "d53b7b35-5e89-4d23-8d0c-1070f30366aa"
          },
          "dapAn": "to keep",
          "isCorrect": true
        },
        {
          "_id": {
            "$oid": "12ca8174-2c98-4588-860d-5d82f26d16af"
          },
          "dapAn": "them small.",
          "isCorrect": true
        }
      ]
    }
  ]
}