{
  "dangCauHoi": "P7",
  "elementType": "WRITING",
  "danhSachCauHoi": [
    {
      "_id": {
        "$oid": "96a5e108-efa1-40c2-b32c-e4df8f888a22"
      },
      "cauHoiNho": [],
      "cauHoi": "In the future, we might __________ <b><span style=\"color:blue\">(see)</span></b> solar windows on buildings.",
      "yNghia": "Câu có <b>will</b> thì động từ <b>talk</b> theo sau được chia ở dạng nguyên thể là <b>talk</b>. Câu hoàn chỉnh là <b>Today I will <span style=\"color:red\">talk</span> about the future of our homes</b>. <i>(Hôm nay tôi sẽ <span style=\"color:red\">nói </span>về tương lai của ngôi nhà của chúng ta.).</i>",
      "danhSachDapAn": [
        {
          "_id": {
            "$oid": "881a1c1d-fd1c-44bd-859e-928ef5fd1910"
          },
          "dapAn": "talk",
          "isCorrect": true
        }
      ]
    },
    {
      "_id": {
        "$oid": "f68a1385-778e-4ffa-96d0-15379059a81b"
      },
      "cauHoiNho": [],
      "cauHoi": "We'd like __________ <b><span style=\"color:blue\">(focus)</span></b> on energy.",
      "yNghia": "Câu có <b>‘d like</b> thì động từ <b>focus</b> theo sau được chia ở dạng nguyên thể có to là <b>to</b> <b>focus</b>. Câu hoàn chỉnh là <b>We'd like <span style=\"color:red\">to</span> <span style=\"color:red\">focus</span> on energy. </b><i>(Chúng tôi muốn <span style=\"color:red\">tập trung </span>vào nội dung về năng lượng.).</i>",
      "danhSachDapAn": [
        {
          "_id": {
            "$oid": "634253db-d592-44b7-afa4-1e6b7c2c1cef"
          },
          "dapAn": "to focus",
          "isCorrect": true
        }
      ]
    },
    {
      "_id": {
        "$oid": "cfd8b117-4a19-4ed9-8411-91e6c2a36d78"
      },
      "cauHoiNho": [],
      "cauHoi": "The appliances in our houses, such as air conditioners and __________ <b><span style=\"color:blue\">(heaters</span></b><span style=\"color:blue\">)</span>, use a lot of energy.",
      "yNghia": "Vì các danh từ khác ví dụ cho <b>appliance</b> đều là số nhiều nên <b>heater</b> phải chia ở dạng số nhiều là <b>heaters</b>. Câu hoàn chỉnh là <b>The appliances </b><b>in our houses, such as air conditioners and <span style=\"color:red\">heaters</span>, use a lot of energy</b>.<b> </b><i>(Các thiết bị trong nhà của chúng ta, chẳng hạn như máy điều hòa và <span style=\"color:red\">máy sưởi</span>, sử dụng rất nhiều năng lượng.).</i>",
      "danhSachDapAn": [
        {
          "_id": {
            "$oid": "aed079a1-8428-49de-8865-ba770616afde"
          },
          "dapAn": "heaters",
          "isCorrect": true
        }
      ]
    },
    {
      "_id": {
        "$oid": "0c856ee9-44aa-4c6a-9a72-a052530269fc"
      },
      "cauHoiNho": [],
      "cauHoi": "In the future, we are going to __________ <b><span style=\"color:blue\">(use)</span></b> renewable energy such as wind power, wave power and solar power.",
      "yNghia": "Câu có cấu trúc <b>be going to</b> thì động từ <b>use</b> theo sau được chia ở dạng nguyên thể là <b>use</b>. Câu hoàn chỉnh là <b>In the future, we are going to <span style=\"color:red\">use</span> renewable energy such as wind power, wave power and solar power.</b> <i>(Trong tương lai, chúng ta sẽ <span style=\"color:red\">sử dụng </span>năng lượng có thể tái tạo được như năng lượng gió, năng lượng sóng và năng lượng mặt trời.).</i>",
      "danhSachDapAn": [
        {
          "_id": {
            "$oid": "6885e181-59d7-4dd8-a4a4-0a713e347f98"
          },
          "dapAn": "use",
          "isCorrect": true
        }
      ]
    },
    {
      "_id": {
        "$oid": "1386f26d-3682-43c0-abe1-65bc84ba6f77"
      },
      "cauHoiNho": [],
      "cauHoi": "These __________ <b><span style=\"color:blue\">(receive)</span></b> sunlight on sunny days.",
      "yNghia": "Vì câu ở thì Hiện tại đơn và chủ ngữ là <b>These</b> chỉ số nhiều nên động từ theo sau <b>receive</b> được chia ở dạng nguyên thể là <b>receive</b>. Câu hoàn chỉnh là <b>These <span style=\"color:red\">receive</span> sunlight on sunny days.</b><i> (Chúng <span style=\"color:red\">nhận được </span>ánh sáng mặt trời vào những ngày nắng.).</i>",
      "danhSachDapAn": [
        {
          "_id": {
            "$oid": "198c6003-87cc-4f51-9eec-832e5bbdf567"
          },
          "dapAn": "receive",
          "isCorrect": true
        }
      ]
    },
    {
      "_id": {
        "$oid": "59931a3c-3e7e-4f2f-b606-c7563950fc36"
      },
      "cauHoiNho": [],
      "cauHoi": "Can you __________ <b><span style=\"color:blue\">(tell)</span></b> us how we can get the electricity?",
      "yNghia": "Câu có <b>can</b> thì động từ <b>tell</b> theo sau được chia ở dạng nguyên thể là <b>tell</b>. Câu hoàn chỉnh là <b>Can you <span style=\"color:red\">tell</span> us how we can get the electricity?</b><i> (Bạn có thể <span style=\"color:red\">cho </span>chúng tôi <span style=\"color:red\">biết </span>làm thế nào chúng ta có thể có điện được không?).</i>",
      "danhSachDapAn": [
        {
          "_id": {
            "$oid": "bfa26f5f-80ee-4883-83dd-33722c6a892e"
          },
          "dapAn": "tell",
          "isCorrect": true
        }
      ]
    },
    {
      "_id": {
        "$oid": "f17593dc-0c54-41cc-a0c1-cde4fabfc144"
      },
      "cauHoiNho": [],
      "cauHoi": "The light falls on special materials, which __________<b><span style=\"color:blue\"> (create)</span></b> electricity.",
      "yNghia": "<b>which</b> là đại từ quan hệ bổ nghĩa cho vế trước nên động từ theo sau <b>create</b> được chia ở dạng số ít là <b>create</b><b>s</b>. Câu hoàn chỉnh là <b>The light falls on special materials, which <span style=\"color:red\">creates</span> electricity</b>. <i>(Ánh sáng chiếu vào những vật liệu đặc biệt, những vật liệu mà <span style=\"color:red\">tạo ra </span>điện.).</i>",
      "danhSachDapAn": [
        {
          "_id": {
            "$oid": "42b1cdbc-1577-4fc0-8d1c-ac5fb997461a"
          },
          "dapAn": "creates",
          "isCorrect": true
        }
      ]
    },
    {
      "_id": {
        "$oid": "d79b2a08-d76d-4993-8b98-01b8bb638dc9"
      },
      "cauHoiNho": [],
      "cauHoi": "This electricity __________ <b><span style=\"color:blue\">(go)</span></b> to the inverter from the solar panels, which changes the DC into AC.",
      "yNghia": "<b>This electricity</b> là chủ ngữ số ít trong câu nên động từ theo sau <b>go </b>được chia là <b>goes</b>. Câu hoàn chỉnh là <b>This electricity <span style=\"color:red\">goes</span> to the inverter from the solar panels, which changes the DC into AC.</b> <i>(Điện này <span style=\"color:red\">đi </span>đến bộ biến tần từ các tấm quang năng, biến đổi DC thành AC.).</i>",
      "danhSachDapAn": [
        {
          "_id": {
            "$oid": "2fbec91a-1cdb-4c35-b735-217564d1e76b"
          },
          "dapAn": "goes",
          "isCorrect": true
        }
      ]
    },
    {
      "_id": {
        "$oid": "04be6eb1-1f4b-483c-aede-a1f5dabe29b6"
      },
      "cauHoiNho": [],
      "cauHoi": "It then sends the electricity to the _______________ <b><span style=\"color:blue\">(appliance)</span></b> such as the kitchen stove, the dishwasher, and washing machine.",
      "yNghia": "Vì các danh từ ví dụ cho <b>appliance</b> đều là số nhiều nên <b>appliance</b> phải chia ở dạng số nhiều là <b>appliances</b>. Câu hoàn chỉnh là <b>It then sends the electricity to the <span style=\"color:red\">appliances</span> such as the kitchen stove, the dishwasher, and washing machine.</b> <i>(Sau đó, nó truyền điện đến <span style=\"color:red\">các thiết bị</span> như bếp lò, máy rửa chén và máy giặt.).</i>",
      "danhSachDapAn": [
        {
          "_id": {
            "$oid": "aea1d205-be88-41b8-be92-8ee7280c3ae2"
          },
          "dapAn": "appliances",
          "isCorrect": true
        }
      ]
    },
    {
      "_id": {
        "$oid": "32ef514a-3023-45e2-9d6f-947497f0a514"
      },
      "cauHoiNho": [],
      "cauHoi": "Sometimes, the system __________<b><span style=\"color:blue\"> (create)</span></b> a lot of energy and the electrical grid takes the power that the house doesn't need.",
      "yNghia": "<b>the system </b>là chủ ngữ danh từ số ít nên động từ <b>create</b> theo sau được chia là <b>creates</b>. Câu hoàn chỉnh là <b>Sometimes, the system <span style=\"color:red\">creates</span> a lot of energy and the electrical grid takes the power that the house doesn't need</b>.<i>(Đôi khi, hệ thống <span style=\"color:red\">tạo ra </span>rất nhiều năng lượng và lưới điện lấy năng lượng mà ngôi nhà không cần.).</i>",
      "danhSachDapAn": [
        {
          "_id": {
            "$oid": "75e9a706-9af3-4337-ad7e-6de6a87f8b37"
          },
          "dapAn": "creates",
          "isCorrect": true
        }
      ]
    },
    {
      "_id": {
        "$oid": "13f44088-b736-497c-ae54-cc9b0577cbb6"
      },
      "cauHoiNho": [],
      "cauHoi": "In the future, we might __________ <b><span style=\"color:blue\">(see)</span></b> solar windows on buildings.",
      "yNghia": "Câu có <b>might</b> thì động từ theo sau <b>see</b> được chia ở dạng nguyên thể là<b> see</b>. Câu hoàn chỉnh là <b>In the future, we might <span style=\"color:red\">see </span>solar windows on buildings.</b><i>(Trong tương lai, chúng ta có thể <span style=\"color:red\">thấy </span>cửa sổ năng lượng mặt trời trên các tòa nhà.).</i>",
      "danhSachDapAn": [
        {
          "_id": {
            "$oid": "6074b3c4-1d61-4a99-93bf-8b73565e900a"
          },
          "dapAn": "see",
          "isCorrect": true
        }
      ]
    },
    {
      "_id": {
        "$oid": "e0985633-cc3a-42e9-8bde-52e399046ee3"
      },
      "cauHoiNho": [],
      "cauHoi": "We could also see solar clothes or solar _______________<b> </b><b><span style=\"color:blue\">(sunglasses)</span></b>.",
      "yNghia": "Vì danh từ <b>solar clothes</b> là số nhiều nên <b>sunglass</b> phải chia ở dạng số nhiều là <b>sunglasses</b>. Câu hoàn chỉnh là <b>We could also see solar clothes or solar <span style=\"color:red\">sunglasses</span>.</b><i>(Chúng ta cũng có thể thấy quần áo năng lượng mặt trời hoặc <span style=\"color:red\">kính râm</span> năng lượng mặt trời.).</i>",
      "danhSachDapAn": [
        {
          "_id": {
            "$oid": "1401f244-ae49-4dab-a975-a330042e05b6"
          },
          "dapAn": "sunglasses",
          "isCorrect": true
        }
      ]
    },
    {
      "_id": {
        "$oid": "0c9fa916-972d-4dce-bbb8-27dfc0fb7c30"
      },
      "cauHoiNho": [],
      "cauHoi": "How useful they _____ <b><span style=\"color:blue\">(be)</span></b>!",
      "yNghia": "Chủ ngữ <b>they</b> là ngôi thứ ba số nhiều nên động từ to be theo sau là <b>are</b>. Câu hoàn chỉnh là <b>How useful they <span style=\"color:red\">are</span>!</b> <i>(Chúng thật hữu ích làm sao!).</i>",
      "danhSachDapAn": [
        {
          "_id": {
            "$oid": "6d6bf57b-67db-404c-9fe3-1c495d0b05b0"
          },
          "dapAn": "are",
          "isCorrect": true
        }
      ]
    },
    {
      "_id": {
        "$oid": "92e8c462-9f75-4646-bdf4-e26e032e6f56"
      },
      "cauHoiNho": [],
      "cauHoi": "We can't __________ <b><span style=\"color:blue\">(use)</span></b> energy from fossil fuels forever.",
      "yNghia": "Câu có <b>can't</b> thì động từ <b>use</b> theo sau được chia ở dạng nguyên thể là <b>use</b>. Câu hoàn chỉnh là<b> </b><b>We can't <span style=\"color:red\">use</span> energy from fossil fuels forever.</b><i>(Chúng ta không thể <span style=\"color:red\">sử dụng </span>năng lượng từ nhiên liệu hóa thạch mãi được.).</i>",
      "danhSachDapAn": [
        {
          "_id": {
            "$oid": "25d472b7-a7a9-4a2f-93e2-5de96c00b056"
          },
          "dapAn": "use",
          "isCorrect": true
        }
      ]
    },
    {
      "_id": {
        "$oid": "1176bed0-d925-4510-bc45-b7c62aab6104"
      },
      "cauHoiNho": [],
      "cauHoi": "If she __________ <b><span style=\"color:blue\">(eat)</span></b> more fish, she will improve her memory.",
      "yNghia": "Trong câu điều kiện loại 1, động từ<b> eat </b>ở mệnh đề<b> if </b>được chia ở thì Hiện tại đơn<b> </b>là <b>eats</b>. Câu hoàn chỉnh là <b>If she <span style=\"color:red\">eats</span> more fish, she will improve her memory</b>.<i>(Nếu cô ấy <span style=\"color:red\">ăn </span>nhiều cá, cô ấy sẽ cải thiện được trí nhớ của mình.).</i>",
      "danhSachDapAn": [
        {
          "_id": {
            "$oid": "4c11b09a-18f9-4d87-8176-3a4659ae93ed"
          },
          "dapAn": "eats",
          "isCorrect": true
        }
      ]
    },
    {
      "_id": {
        "$oid": "f8fcfcbe-e86b-4ab3-bcdc-6c2f7548d0af"
      },
      "cauHoiNho": [],
      "cauHoi": "I know that if I sleep for at least eight hours, I always __________ <b><span style=\"color:blue\">(</span></b><b><span style=\"color:blue\">feel)</span></b><i> </i>more intelligent the next day!",
      "yNghia": "Trong câu điều kiện loại 0, động từ<b> feel </b>ở mệnh đề<b> </b>chính được chia ở thì Hiện tại đơn<b> </b>là <b>feel</b>. Câu hoàn chỉnh là <b>I know that if I sleep for at least eight hours, I always <span style=\"color:red\">feel</span> more intelligent the next day!</b><i>(Tôi biết rằng nếu tôi ngủ ít nhất 8 tiếng, tôi luôn <span style=\"color:red\">cảm thấy</span> mình thông minh hơn vào ngày hôm sau!).</i>",
      "danhSachDapAn": [
        {
          "_id": {
            "$oid": "ee2540d4-c117-43dc-a79e-c816194bfae4"
          },
          "dapAn": "feel",
          "isCorrect": true
        }
      ]
    },
    {
      "_id": {
        "$oid": "16e7607f-ee4c-431a-9bdd-4c780439020d"
      },
      "cauHoiNho": [],
      "cauHoi": "I __________ <b><span style=\"color:blue\">(</span></b><b><span style=\"color:blue\">be)</span></b> so tired when I get home late.",
      "yNghia": "Câu mang nghĩa tương lai sử dụng Hiện tại đơn và chủ ngữ<b> I </b>là ngôi thứ nhất số ít nên động từ to be được chia là<b> am</b>. Câu hoàn chỉnh là <b>I <span style=\"color:red\">am </span>so tired when I get home late.</b><i>(Tôi sẽ rất mệt khi tôi về nhà muộn.).</i>",
      "danhSachDapAn": [
        {
          "_id": {
            "$oid": "809cdc7b-0eec-4af2-98d2-4265d1ad3998"
          },
          "dapAn": "am",
          "isCorrect": true
        }
      ]
    },
    {
      "_id": {
        "$oid": "95a2658e-6d6c-4bec-950c-61f2ce5c6ae2"
      },
      "cauHoiNho": [],
      "cauHoi": "__________ <b><span style=\"color:blue\">(</span></b><b><span style=\"color:blue\">talk)</span></b> to people in person will improve your attention.",
      "yNghia": "Động từ <b>Talk </b>đứng ở đầu câu được sử dụng như danh từ thì được chia ở dạng động từ đuôi -ing là <b>Talking</b>. Câu hoàn chỉnh là <b><span style=\"color:red\">Talking</span></b><b> to people in person will improve your attention.</b><i> (<span style=\"color:red\">Nói chuyện </span>trực tiếp với mọi người sẽ cải thiện sự chú ý của bạn.).</i>",
      "danhSachDapAn": [
        {
          "_id": {
            "$oid": "d8d564db-c1a7-4612-92ab-f1c2eab7218e"
          },
          "dapAn": "Talking",
          "isCorrect": true
        }
      ]
    },
    {
      "_id": {
        "$oid": "65a9cb09-45a2-44bb-814c-91c1c30dcfee"
      },
      "cauHoiNho": [],
      "cauHoi": "I think we will __________ <b><span style=\"color:blue\">(see)</span></b> big changes in entertainment.",
      "yNghia": "Câu có <b>will</b> thì động từ <b>see</b> theo sau được chia ở dạng nguyên thể là <b>see</b>. Câu hoàn chỉnh là <b>I think we will <span style=\"color:red\">see</span> big changes in entertainment.</b> <i>(Tôi nghĩ là chúng ta sẽ <span style=\"color:red\">thấy </span>sự thay đổi to lớn trong ngành giải trí.).</i>",
      "danhSachDapAn": [
        {
          "_id": {
            "$oid": "618e5058-d6cb-4dde-ab51-39457c55ec9b"
          },
          "dapAn": "see",
          "isCorrect": true
        }
      ]
    },
    {
      "_id": {
        "$oid": "09be917e-abd7-4a53-b336-63f7c7375544"
      },
      "cauHoiNho": [],
      "cauHoi": "Some studies found that if you exercise for 10 minutes before __________ <b><span style=\"color:blue\">(</span></b><b><span style=\"color:blue\">think)</span></b> about a problem, it improves your problem-solving and decision-making skills.",
      "yNghia": "Câu có <b>before </b>thì động từ <b>think</b> theo sau được chia ở dạng động từ đuôi -ing là <b>thinking</b>. Câu hoàn chỉnh là <b>Some studies found that if you exercise for 10 minutes before <span style=\"color:red\">thinking</span> about a problem, it improves your problem-solving and decision-making skills.</b> <i>(Một số nghiên cứu cho thấy rằng nếu bạn tập thể dục trong 10 phút trước khi <span style=\"color:red\">nghĩ </span>về một vấn đề, nó sẽ cải thiện kỹ năng giải quyết vấn đề và đưa ra quyết định của bạn.)</i>",
      "danhSachDapAn": [
        {
          "_id": {
            "$oid": "fd52c495-0d60-413b-bb09-2880ffe7e823"
          },
          "dapAn": "thinking",
          "isCorrect": true
        }
      ]
    }
  ]
}